zc/recipe/egg/README.rst
zc/recipe/egg/__init__.py
zc/recipe/egg/api.rst
zc/recipe/egg/custom.py
zc/recipe/egg/custom.rst
zc/recipe/egg/egg.py
zc/recipe/egg/tests.py
zc/recipe/egg/working_set_caching.rst
zc_recipe_egg-4.0.0.dist-info/METADATA
zc_recipe_egg-4.0.0.dist-info/WHEEL
zc_recipe_egg-4.0.0.dist-info/entry_points.txt
zc_recipe_egg-4.0.0.dist-info/top_level.txt
zc_recipe_egg-4.0.0.dist-info/RECORD
