Metadata-Version: 2.4
Name: zc.recipe.egg
Version: 4.0.0
Summary: Recipe for installing Python package distributions as eggs
Home-page: https://github.com/buildout/buildout/tree/master/zc.recipe.egg_
Author: Jim Fulton
Author-email: jim@zope.com
License: ZPL 2.1
Keywords: development build
Classifier: Development Status :: 6 - Mature
Classifier: Framework :: Buildout
Classifier: Intended Audience :: Developers
Classifier: License :: OSI Approved :: Zope Public License
Classifier: Programming Language :: Python
Classifier: Programming Language :: Python :: 3.9
Classifier: Programming Language :: Python :: 3.10
Classifier: Programming Language :: Python :: 3.11
Classifier: Programming Language :: Python :: 3.12
Classifier: Programming Language :: Python :: 3.13
Classifier: Topic :: Software Development :: Build Tools
Classifier: Topic :: Software Development :: Libraries :: Python Modules
Requires-Python: >=3.9
Requires-Dist: zc.buildout>=5.0.0
Requires-Dist: setuptools
Dynamic: author
Dynamic: author-email
Dynamic: classifier
Dynamic: description
Dynamic: home-page
Dynamic: keywords
Dynamic: license
Dynamic: requires-dist
Dynamic: requires-python
Dynamic: summary
